speak2mary/__init__.py
speak2mary-1.5.0.dist-info/LICENCE
speak2mary-1.5.0.dist-info/METADATA
speak2mary-1.5.0.dist-info/WHEEL
speak2mary-1.5.0.dist-info/top_level.txt
speak2mary-1.5.0.dist-info/RECORD
