Metadata-Version: 2.1
Name: speak2mary
Version: 1.5.0
Summary: A Python wrapper for Mary TTS
Home-page: https://github.com/Poeschl/speak2mary
Author: Poeschl
License: Apache License - Version 2.0
Platform: UNKNOWN
Classifier: License :: OSI Approved :: Apache Software License
Classifier: Programming Language :: Python :: 3
Classifier: Programming Language :: Python :: 3.6
Classifier: Programming Language :: Python :: 3.7
Classifier: Programming Language :: Python :: 3.8
Classifier: Programming Language :: Python :: 3.9
Requires-Python: >=3
